trackscan/__init__.py
trackscan/cli.py
trackscan/modules/analysis_utils.py
trackscan/modules/curve_fitting.py
trackscan/modules/io_utils.py
trackscan/modules/linking_functions.py
trackscan/modules/make_tracks.py
trackscan/modules/msd_analysis.py
trackscan/modules/track_manipulations.py
trackscan/modules/visualization_utils.py
trackscan-0.0.3.dist-info/METADATA
trackscan-0.0.3.dist-info/WHEEL
trackscan-0.0.3.dist-info/entry_points.txt
trackscan-0.0.3.dist-info/top_level.txt
trackscan-0.0.3.dist-info/RECORD
