Metadata-Version: 2.4
Name: trackscan
Version: 0.0.3
Summary: Post-processing and analysis of cell track data
Author: Chris Viets
Project-URL: Homepage, https://github.com/cviets/trackscan
Project-URL: Bug Tracker, https://github.com/cviets/trackscan/issues
Requires-Python: >=3.6
Requires-Dist: numpy
Requires-Dist: matplotlib
Requires-Dist: scipy
